README
setup.py
./inparallel/__init__.py
./inparallel/task.py
./inparallel/util.py
./inparallel/waitfor.py
inparallel.egg-info/PKG-INFO
inparallel.egg-info/SOURCES.txt
inparallel.egg-info/dependency_links.txt
inparallel.egg-info/requires.txt
inparallel.egg-info/top_level.txt