Metadata-Version: 1.1
Name: inparallel
Version: 1.0.3
Summary: A novel take on process-based parallelism in Python (CPython 2.7 or 3.4+)
Home-page: https://github.com/AlexForster/inparallel
Author: Alex Forster
Author-email: alex@alexforster.com
License: 3-Clause ("New") BSD license
Download-URL: https://pypi.python.org/pypi/inparallel
Platform: UNKNOWN
Classifier: Development Status :: 5 - Production/Stable
Classifier: Intended Audience :: Developers
Classifier: License :: OSI Approved :: BSD License
Classifier: Operating System :: MacOS :: MacOS X
Classifier: Operating System :: POSIX
Classifier: Operating System :: POSIX :: BSD
Classifier: Operating System :: POSIX :: Linux
Classifier: Programming Language :: Python
Classifier: Programming Language :: Python :: 2
Classifier: Programming Language :: Python :: 2.7
Classifier: Programming Language :: Python :: 3
Classifier: Programming Language :: Python :: 3.4
Classifier: Programming Language :: Python :: 3.5
Classifier: Topic :: Software Development :: Libraries
